LICENSE
MANIFEST.in
README.rst
requirements.txt
setup.py
images/logging_fortified.png
pyfortified_logging_slim/__init__.py
pyfortified_logging_slim/logger_adapter_custom.py
pyfortified_logging_slim/logger_json_lexer.py
pyfortified_logging_slim/logging.py
pyfortified_logging_slim/logging_format.py
pyfortified_logging_slim/logging_json_formatter.py
pyfortified_logging_slim/logging_levels.py
pyfortified_logging_slim/logging_output.py
pyfortified_logging_slim.egg-info/PKG-INFO
pyfortified_logging_slim.egg-info/SOURCES.txt
pyfortified_logging_slim.egg-info/dependency_links.txt
pyfortified_logging_slim.egg-info/not-zip-safe
pyfortified_logging_slim.egg-info/requires.txt
pyfortified_logging_slim.egg-info/top_level.txt
pyfortified_logging_slim/errors/__init__.py
pyfortified_logging_slim/errors/errors_traceback.py
pyfortified_logging_slim/support/__init__.py
pyfortified_logging_slim/support/singleton.py