Metadata-Version: 1.1
Name: pyfortified-logging-slim
Version: 0.1.10
Summary: Extension to Python `logging` functionality.
Home-page: https://github.com/jeff00seattle/pyfortified-logging
Author: UNKNOWN
Author-email: UNKNOWN
License: MIT License
Download-URL: https://github.com/jeff00seattle/pyfortified-logging/archive/v0.1.10.tar.gz
Keywords: pyfortified logging
Platform: UNKNOWN
Classifier: Development Status :: 3 - Alpha
Classifier: Intended Audience :: Developers
Classifier: Natural Language :: English
Classifier: License :: OSI Approved :: MIT License
Classifier: Operating System :: OS Independent
Classifier: Natural Language :: English
Classifier: Programming Language :: Python
Classifier: Programming Language :: Python :: 3
Classifier: Programming Language :: Python :: 3.4
Classifier: Programming Language :: Python :: 3.5
Classifier: Programming Language :: Python :: 3.6
Classifier: Topic :: Software Development :: Libraries :: Python Modules
